nalangTest/test1.py
nalangTest/test2.py
nalangTest-0.0.0.3.dist-info/METADATA
nalangTest-0.0.0.3.dist-info/WHEEL
nalangTest-0.0.0.3.dist-info/top_level.txt
nalangTest-0.0.0.3.dist-info/RECORD
