Metadata-Version: 2.1
Name: nalangTest
Version: 0.0.0.3
Summary: My First Test Package
Home-page: https://lingua.blog.me/…
Author: Sukjae Choi
Author-email: lingua72@gmail.com
License: MIT
Requires-Python: >=3
